ha_synthetic_sensors/__init__.py
ha_synthetic_sensors/alternate_state_circular_validator.py
ha_synthetic_sensors/alternate_state_eval.py
ha_synthetic_sensors/alternate_state_processor.py
ha_synthetic_sensors/alternate_state_type_analyzer.py
ha_synthetic_sensors/alternate_state_utils.py
ha_synthetic_sensors/boolean_states.py
ha_synthetic_sensors/cache.py
ha_synthetic_sensors/collection_resolver.py
ha_synthetic_sensors/condition_parser.py
ha_synthetic_sensors/config_helpers/yaml_helpers.py
ha_synthetic_sensors/config_loader.py
ha_synthetic_sensors/config_manager.py
ha_synthetic_sensors/config_models.py
ha_synthetic_sensors/config_types.py
ha_synthetic_sensors/config_yaml_converter.py
ha_synthetic_sensors/constants_alternate.py
ha_synthetic_sensors/constants_boolean_states.py
ha_synthetic_sensors/constants_device.py
ha_synthetic_sensors/constants_entities.py
ha_synthetic_sensors/constants_error_strings.py
ha_synthetic_sensors/constants_evaluation_results.py
ha_synthetic_sensors/constants_formula.py
ha_synthetic_sensors/constants_handlers.py
ha_synthetic_sensors/constants_metadata.py
ha_synthetic_sensors/constants_types.py
ha_synthetic_sensors/core_formula_evaluator.py
ha_synthetic_sensors/cross_sensor_reference_detector.py
ha_synthetic_sensors/cross_sensor_reference_manager.py
ha_synthetic_sensors/cross_sensor_reference_reassignment.py
ha_synthetic_sensors/data_validation.py
ha_synthetic_sensors/datetime_functions/__init__.py
ha_synthetic_sensors/datetime_functions/base_datetime_function.py
ha_synthetic_sensors/datetime_functions/date_functions.py
ha_synthetic_sensors/datetime_functions/datetime_handler.py
ha_synthetic_sensors/datetime_functions/duration_functions.py
ha_synthetic_sensors/datetime_functions/function_registry.py
ha_synthetic_sensors/datetime_functions/protocol.py
ha_synthetic_sensors/datetime_functions/timezone_functions.py
ha_synthetic_sensors/dependency_parser.py
ha_synthetic_sensors/dependency_resolver.py
ha_synthetic_sensors/device_association.py
ha_synthetic_sensors-1.1.12.dist-info/LICENSE
ha_synthetic_sensors-1.1.12.dist-info/METADATA
ha_synthetic_sensors-1.1.12.dist-info/WHEEL
ha_synthetic_sensors-1.1.12.dist-info/RECORD
