Metadata-Version: 2.3
Name: ha-synthetic-sensors
Version: 1.1.12
Summary: A Home Assistant package for creating synthetic sensors from YAML configuration with mathematical formulas
Author: Bill Flood
Requires-Python: >=3.13.2,<3.14
Classifier: Programming Language :: Python :: 3
Requires-Dist: aiofiles
Requires-Dist: homeassistant (>=2025.8.2,<2026.0.0)
Requires-Dist: jsonschema (>=4.24.0,<5.0.0)
Requires-Dist: simpleeval (>=1.0.3,<2.0.0)
Project-URL: Homepage, https://github.com/LegoTypes/ha-synthetic-sensors
Project-URL: Issues, https://github.com/LegoTypes/ha-synthetic-sensors/issues
